LICENSE.txt
README.md
pyproject.toml
setup.py
PyNetstockQuoteLib/PyNetstockQuoteLib.pyd
PyNetstockQuoteLib/PyNetstockQuoteLib.pyi
PyNetstockQuoteLib/README.md
PyNetstockQuoteLib/__init__.py
PyNetstockQuoteLib/define.py
PyNetstockQuoteLib.egg-info/PKG-INFO
PyNetstockQuoteLib.egg-info/SOURCES.txt
PyNetstockQuoteLib.egg-info/dependency_links.txt
PyNetstockQuoteLib.egg-info/top_level.txt