Metadata-Version: 2.4
Name: PyNetstockQuoteLib
Version: 1.0.10
Summary: 兆源股份有限公司(FISTEK)提供台股報價API
Author-email: WeiTian <twccad@163.com>
Classifier: Operating System :: Microsoft :: Windows :: Windows 7
Classifier: Operating System :: Microsoft :: Windows :: Windows 8
Classifier: Operating System :: Microsoft :: Windows :: Windows 8.1
Classifier: Operating System :: Microsoft :: Windows :: Windows 10
Classifier: Operating System :: Microsoft :: Windows :: Windows 11
Classifier: Programming Language :: Python :: 3
Requires-Python: >=3.8
License-File: LICENSE.txt
Dynamic: license-file
